msensortools/__init__.py
msensortools/example_main.py
msensortools/make_proto.py
msensortools/sim_adapter.py
msensortools/protobuf/__init__.py
msensortools/protobuf/morai_actor_pb2.py
msensortools/protobuf/morai_actor_pb2_grpc.py
msensortools/protobuf/morai_mgeo_pb2.py
msensortools/protobuf/morai_mgeo_pb2_grpc.py
msensortools/protobuf/morai_sensor_pb2.py
msensortools/protobuf/morai_sensor_pb2_grpc.py
msensortools/protobuf/morai_sim_info_pb2.py
msensortools/protobuf/morai_sim_info_pb2_grpc.py
msensortools/protobuf/morai_simulation_pb2.py
msensortools/protobuf/morai_simulation_pb2_grpc.py
msensortools/protobuf/morai_type_pb2.py
msensortools/protobuf/morai_type_pb2_grpc.py
msensortools-0.0.3.dist-info/LICENSE.txt
msensortools-0.0.3.dist-info/METADATA
msensortools-0.0.3.dist-info/WHEEL
msensortools-0.0.3.dist-info/top_level.txt
msensortools-0.0.3.dist-info/RECORD
